<?xml version="1.0"?>
<opencv_storage>
<stage25>
  <maxWeakCount>12</maxWeakCount>
  <stageThreshold>-9.4462507963180542e-01</stageThreshold>
  <weakClassifiers>
    <_>
      <internalNodes>
        0 -1 28593 -1113453999 2080046975 -5312769 703508287 -1375912049
        -1241514115 1862106347 741607456</internalNodes>
      <leafValues>
        -3.1098264455795288e-01 4.7344633936882019e-01</leafValues></_>
    <_>
      <internalNodes>
        0 -1 26037 -11740970 468952605 -1140934727 -47663262 1416592105
        2138177142 -1684015874 -1122461765</internalNodes>
      <leafValues>
        -2.8580358624458313e-01 5.4876589775085449e-01</leafValues></_>
    <_>
      <internalNodes>
        0 -1 3624 -1821715751 1407663231 921626106 866936562 -1472267425
        -544821322 -1909707196 -632740523</internalNodes>
      <leafValues>
        -2.6510763168334961e-01 6.3888806104660034e-01</leafValues></_>
    <_>
      <internalNodes>
        0 -1 37689 1409970298 -1718926708 1048577 85526043 1086423552
        557058 -1601901671 1872990376</internalNodes>
      <leafValues>
        -4.6812927722930908e-01 4.1546446084976196e-01</leafValues></_>
    <_>
      <internalNodes>
        0 -1 38777 29459038 -720107428 -2130640565 -1761345381
        1478566105 1493368984 1082271791 713312276</internalNodes>
      <leafValues>
        -4.5201742649078369e-01 4.2546343803405762e-01</leafValues></_>
    <_>
      <internalNodes>
        0 -1 36838 -1023541316 862812128 2136903872 -819527688
        -1229455907 1484611360 1205854163 -715710465</internalNodes>
      <leafValues>
        -3.4161305427551270e-01 5.9638547897338867e-01</leafValues></_>
    <_>
      <internalNodes>
        0 -1 20452 -45132312 -548203443 -940183569 -889366595
        -1929844696 -1342181524 117436095 -863259669</internalNodes>
      <leafValues>
        -3.3631253242492676e-01 6.2174969911575317e-01</leafValues></_>
    <_>
      <internalNodes>
        0 -1 2369 -85209345 -155718728 1333657325 -1557926148 1738974892
        1334267895 1827587808 1626306559</internalNodes>
      <leafValues>
        -3.3825248479843140e-01 6.1095768213272095e-01</leafValues></_>
    <_>
      <internalNodes>
        0 -1 37960 952084533 -1619595288 -16779585 120569519 -8947764
        -578846850 -4229681 -1403984608</internalNodes>
      <leafValues>
        -3.1621900200843811e-01 6.2303090095520020e-01</leafValues></_>
    <_>
      <internalNodes>
        0 -1 39097 264220334 1718861160 -306258129 280247546 -302533264
        893222356 -224497938 -166854674</internalNodes>
      <leafValues>
        -4.3301555514335632e-01 4.8635375499725342e-01</leafValues></_>
    <_>
      <internalNodes>
        0 -1 19233 -1506467229 -835271151 2137651445 -1611727171
        1668506953 -469833793 -1093588337 -302191107</internalNodes>
      <leafValues>
        -4.0373295545578003e-01 5.4592156410217285e-01</leafValues></_>
    <_>
      <internalNodes>
        0 -1 19413 -599010850 -17092611 1585004541 268270226 1593212344
        536444799 2105073514 261238453</internalNodes>
      <leafValues>
        -4.2916810512542725e-01 5.3011000156402588e-01</leafValues></_></weakClassifiers></stage25>
</opencv_storage>
